kspies.libs/libgfortran-ed201abd.so.3.0.0
kspies.libs/liblapack-78e59728.so.3.0.3
kspies.libs/libgfortran-bfa58d52.so.1.0.0
kspies.libs/libblas-2d5b9174.so.3.0.3
kspies/__init__.py
kspies/zmp.py
kspies/kspies_fort.cpython-36m-x86_64-linux-gnu.so
kspies/util.py
kspies/wy.py
kspies-1.0.3.dist-info/METADATA
kspies-1.0.3.dist-info/top_level.txt
kspies-1.0.3.dist-info/RECORD
kspies-1.0.3.dist-info/WHEEL
kspies-1.0.3.dist-info/LICENSE
fortran_source/kspies_fort.f90
fortran_source/compile.sh
