Metadata-Version: 2.1
Name: kspies
Version: 1.0.3
Summary: This is a python based Kohn-Sham Inversion Evaluation Software package for use with pySCF.
Home-page: https://ssnam92.github.io/KSPies/
Author: Seungsoo Nam,  Ryan J. McCarty, Hansol Park, Eunji Sim
Author-email: skaclitz@yonsei.ac.kr
License: UNKNOWN
Platform: UNKNOWN
Classifier: Programming Language :: Python :: 3
Classifier: License :: OSI Approved :: Apache Software License
Classifier: Operating System :: Unix
Classifier: Development Status :: 4 - Beta
Requires-Python: >=3.6
